{
  "project_info": {
    "project_number": "143489396645",
    "project_id": "jitcall-b72ec",
    "storage_bucket": "jitcall-b72ec.firebasestorage.app"
  },
  "client": [
    {
      "client_info": {
        "mobilesdk_app_id": "1:143489396645:android:b4fb543d642a4b5065c24c",
        "android_client_info": {
          "package_name": "com.compani.jitcalljesus"
        }
      },
      "oauth_client": [],
      "api_key": [
        {
          "current_key": "AIzaSyC_1SjuRr0KpyUNk7vQ0jv2Cvu3wU74Rrc"
        }
      ],
      "services": {
        "appinvite_service": {
          "other_platform_oauth_client": []
        }
      }
    }
  ],
  "configuration_version": "1"
}